runman/__init__.py
runman/main.py
r_task_manager-1.0.3.dist-info/METADATA
r_task_manager-1.0.3.dist-info/WHEEL
r_task_manager-1.0.3.dist-info/entry_points.txt
r_task_manager-1.0.3.dist-info/top_level.txt
r_task_manager-1.0.3.dist-info/RECORD
